infernal/__init__.py
infernal/common/__init__.py
infernal/common/utils.py
infernal/core/__init__.py
infernal/core/exception.py
infernal/core/service.py
infernal/core/session.py
infernal/core/static.py
infernal/graphics/__init__.py
infernal/services/__metadata__/errors.json
infernal/services/__metadata__/regions.json
infernal/services/__templates__/paginators.json
infernal/services/__templates__/service_v1.json
infernal/services/__templates__/service_v2.json
infernal/services/lol-champion/service.json
infernal/services/lol-champion-mastery/service.json
infernal/services/lol-league/service.json
infernal/services/lol-league-exp/service.json
infernal/services/lol-match/service.json
infernal/services/lol-spectator/service.json
infernal/services/lol-status/service.json
infernal/services/lol-summoner/service.json
infernal/services/lol-third-party-code/service.json
infernal/services/lol-tournament/service.json
infernal/services/lol-tournament-stub/service.json
infernal-0.0.0.dist-info/LICENSE
infernal-0.0.0.dist-info/WHEEL
infernal-0.0.0.dist-info/METADATA
infernal-0.0.0.dist-info/RECORD
