Metadata-Version: 2.1
Name: infernal
Version: 0.0.0
Summary: Core library for the Infernal eSports Analytics Infernal library.
Author: Shparki
Author-email: murrmat@gmail.com
Requires-Python: >=3.7,<4.0
Classifier: Programming Language :: Python :: 3
Classifier: Programming Language :: Python :: 3.7
Classifier: Programming Language :: Python :: 3.8
Requires-Dist: requests (>=2.23.0,<3.0.0)
Requires-Dist: selenium (>=3.141.0,<4.0.0)
Requires-Dist: vaex (>=3.0.0,<4.0.0)
